covid_data/__init__.py
covid_data/__main__.py
covid_data/covid_data.py
covid_data/errors.py
covid_data/logger.py
covid_data/types.py
covid_data/commands/__init__.py
covid_data/commands/fix_locations.py
covid_data/commands/load_csv.py
covid_data/commands/scrap_country.py
covid_data/commands/test_load_csv.py
covid_data/db/__init__.py
covid_data/db/queries.py
covid_data/db/test_queries.py
covid_data/scrappers/__init__.py
covid_data/scrappers/france.py
covid_data/scrappers/spain.py
covid_data/test_utils/__init__.py
covid_data/utils/__init__.py
covid_data/utils/components_hierarchy.py
covid_data/utils/components_mapping.py
covid_data/utils/places.py
covid_data-0.1.21.dist-info/METADATA
covid_data-0.1.21.dist-info/WHEEL
covid_data-0.1.21.dist-info/entry_points.txt
covid_data-0.1.21.dist-info/top_level.txt
covid_data-0.1.21.dist-info/RECORD
