Metadata-Version: 2.1
Name: covid-data
Version: 0.1.21
Summary: Data loader part of the mid-project for the Data Science bootcamp from Core Code School
Home-page: https://github.com/alesanmed-educational-projects/covid-data
Author: alesanchez
Author-email: hi@alesanchez.es
License: The Unlicense
Download-URL: https://github.com/alesanmed-educational-projects/covid-data/archive/refs/tags/0.1.21.tar.gz
Keywords: covid,core
Platform: UNKNOWN
Classifier: Development Status :: 3 - Alpha
Classifier: Intended Audience :: Developers
Classifier: Topic :: Scientific/Engineering :: Information Analysis
Classifier: License :: OSI Approved :: The Unlicense (Unlicense)
Classifier: Programming Language :: Python :: 3
Requires-Dist: beautifulsoup4 (==4.9.3)
Requires-Dist: certifi (==2021.5.30)
Requires-Dist: charset-normalizer (==2.0.4)
Requires-Dist: click (==8.0.1)
Requires-Dist: colorama (==0.4.4)
Requires-Dist: idna (==3.2)
Requires-Dist: numpy (==1.21.1)
Requires-Dist: pandas (>=1.3.0)
Requires-Dist: psycopg2 (==2.9.1)
Requires-Dist: python-dateutil (==2.8.2)
Requires-Dist: python-dotenv (==0.19.0)
Requires-Dist: pytz (==2021.1)
Requires-Dist: requests (==2.26.0)
Requires-Dist: six (==1.16.0)
Requires-Dist: soupsieve (==2.2.1)
Requires-Dist: unidecode (==1.2.0)
Requires-Dist: urllib3 (==1.26.6)
